src/__init__.py
src/imsdk/__init__.py
src/imsdk/engine.py
src/imsdk/util.py
src/rc_im_mcp_demo.egg-info/PKG-INFO
src/rc_im_mcp_demo.egg-info/SOURCES.txt
src/rc_im_mcp_demo.egg-info/dependency_links.txt
src/rc_im_mcp_demo.egg-info/requires.txt
src/rc_im_mcp_demo.egg-info/top_level.txt
src/server/__init__.py
src/server/server.py
src/utils/__init__.py
src/utils/mcp_utils.py
test_lhy_mcp_server-0.1.2.dist-info/METADATA
test_lhy_mcp_server-0.1.2.dist-info/WHEEL
test_lhy_mcp_server-0.1.2.dist-info/entry_points.txt
test_lhy_mcp_server-0.1.2.dist-info/RECORD
