Metadata-Version: 2.4
Name: test-lhy-mcp-server
Version: 0.1.2
Summary: test
Project-URL: Homepage, https://github.com/rongcloud/test-lhy-mcp-server
Project-URL: Repository, https://github.com/rongcloud/test-lhy-mcp-server.git
Author-email: Rongcloud <imsdk@rongcloud.cn>
Requires-Python: >=3.10
Requires-Dist: click>=8.0.0
Requires-Dist: mcp[cli]
Requires-Dist: pydantic
Requires-Dist: pydantic-settings
Requires-Dist: uvicorn
Provides-Extra: dev
Requires-Dist: pip-tools; extra == 'dev'
